nautilus_trader/__init__.pxd
nautilus_trader/__init__.py
nautilus_trader/accounting/__init__.pxd
nautilus_trader/accounting/__init__.py
nautilus_trader/accounting/accounts/__init__.pxd
nautilus_trader/accounting/accounts/__init__.py
nautilus_trader/accounting/accounts/base.cpython-311-aarch64-linux-gnu.so
nautilus_trader/accounting/accounts/base.pxd
nautilus_trader/accounting/accounts/base.pyx
nautilus_trader/accounting/accounts/betting.cpython-311-aarch64-linux-gnu.so
nautilus_trader/accounting/accounts/betting.pxd
nautilus_trader/accounting/accounts/betting.pyx
nautilus_trader/accounting/accounts/cash.cpython-311-aarch64-linux-gnu.so
nautilus_trader/accounting/accounts/cash.pxd
nautilus_trader/accounting/accounts/cash.pyx
nautilus_trader/accounting/accounts/margin.cpython-311-aarch64-linux-gnu.so
nautilus_trader/accounting/accounts/margin.pxd
nautilus_trader/accounting/accounts/margin.pyx
nautilus_trader/accounting/calculators.cpython-311-aarch64-linux-gnu.so
nautilus_trader/accounting/calculators.pxd
nautilus_trader/accounting/calculators.pyx
nautilus_trader/accounting/error.py
nautilus_trader/accounting/factory.cpython-311-aarch64-linux-gnu.so
nautilus_trader/accounting/factory.pxd
nautilus_trader/accounting/factory.pyx
nautilus_trader/accounting/manager.cpython-311-aarch64-linux-gnu.so
nautilus_trader/accounting/manager.pxd
nautilus_trader/accounting/manager.pyx
nautilus_trader/accounting/margin_models.cpython-311-aarch64-linux-gnu.so
nautilus_trader/accounting/margin_models.pxd
nautilus_trader/accounting/margin_models.pyx
nautilus_trader/adapters/__init__.py
nautilus_trader/adapters/_template/__init__.py
nautilus_trader/adapters/_template/core.py
nautilus_trader/adapters/_template/data.py
nautilus_trader/adapters/_template/execution.py
nautilus_trader/adapters/_template/providers.py
nautilus_trader/adapters/betfair/__init__.py
nautilus_trader/adapters/betfair/client.py
nautilus_trader/adapters/betfair/common.py
nautilus_trader/adapters/betfair/config.py
nautilus_trader-1.220.0.dist-info/LICENSE
nautilus_trader-1.220.0.dist-info/METADATA
nautilus_trader-1.220.0.dist-info/WHEEL
nautilus_trader-1.220.0.dist-info/RECORD
