Metadata-Version: 2.3
Name: nautilus_trader
Version: 1.220.0
Summary: A high-performance algorithmic trading platform and event-driven backtester
License: LGPL-3.0-or-later
Author: Nautech Systems
Author-email: info@nautechsystems.io
Requires-Python: >=3.11,<3.14
Classifier: License :: OSI Approved :: GNU Lesser General Public License v3 or later (LGPLv3+)
Classifier: Operating System :: OS Independent
Classifier: Development Status :: 4 - Beta
Classifier: Programming Language :: Python :: 3
Classifier: Programming Language :: Python :: 3.11
Classifier: Programming Language :: Python :: 3.12
Classifier: Programming Language :: Python :: 3.13
Classifier: Topic :: Software Development :: Libraries
Classifier: Topic :: Software Development :: Libraries :: Python Modules
Classifier: Topic :: Scientific/Engineering
Classifier: Topic :: Office/Business :: Financial
Classifier: Topic :: Office/Business :: Financial :: Investment
Classifier: Intended Audience :: Developers
Classifier: Intended Audience :: Financial and Insurance Industry
Classifier: Intended Audience :: Science/Research
Provides-Extra: betfair
Provides-Extra: docker
Provides-Extra: dydx
Provides-Extra: ib
Provides-Extra: polymarket
Requires-Dist: bech32 (>=1.2.0,<2.0.0) ; extra == "dydx"
Requires-Dist: betfair-parser (==0.14.4) ; extra == "betfair"
Requires-Dist: bip-utils (>=2.9.3,<3.0.0) ; extra == "dydx"
Requires-Dist: click (>=8.0.0,<9.0.0)
Requires-Dist: defusedxml (>=0.7.1,<1.0.0) ; extra == "ib"
Requires-Dist: docker (>=7.1.0,<8.0.0) ; extra == "docker"
Requires-Dist: ecdsa (>=0.19.0,<1.0.0) ; extra == "dydx"
Requires-Dist: fsspec (>=2025.2.0,<2026.0.0)
Requires-Dist: grpcio (==1.68.1) ; extra == "dydx"
Requires-Dist: msgspec (>=0.19.0,<1.0.0)
Requires-Dist: nautilus-ibapi (==10.30.1) ; extra == "ib"
Requires-Dist: numpy (>=1.26.4)
Requires-Dist: pandas (>=2.2.3,<3.0.0)
Requires-Dist: portion (>=2.6.1)
Requires-Dist: protobuf (==5.29.1) ; extra == "dydx"
Requires-Dist: py-clob-client (==0.23.0) ; extra == "polymarket"
Requires-Dist: pyarrow (>=20.0.0)
Requires-Dist: pycryptodome (>=3.20.0,<4.0.0) ; extra == "dydx"
Requires-Dist: pytz (>=2025.1.0)
Requires-Dist: tqdm (>=4.67.1,<5.0.0)
Requires-Dist: uvloop (>=0.21.0,<1.0.0) ; sys_platform != "win32"
Requires-Dist: v4-proto (==7.0.5) ; extra == "dydx"
Project-URL: Homepage, https://nautilustrader.io
Project-URL: Repository, https://github.com/nautechsystems/nautilus_trader
Project-URL: docs, https://nautilustrader.io/docs
